{
  "rel_path": "第二章_空间理论/2.2_距离空间/image44.jpg",
  "image_path": "docs/第二章_空间理论/2.2_距离空间/image44.jpg",
  "model": "mimo-v2.5",
  "status": "pending",
  "auto_flags": [],
  "raw": "{\n  \"type\": \"judge\",\n  \"seq\": 32,\n  \"points\": 1,\n  \"stem\": \"$\\\\mathbb{R}^3$ 是完备距离空间.\",\n  \"options\": [],\n  \"answer\": \"正确\",\n  \"answer_raw\": \"正确\",\n  \"explanation\": null,\n  \"note\": null\n}",
  "type": "judge",
  "seq": 32,
  "points": 1,
  "stem": "$\\mathbb{R}^3$ 是完备距离空间.",
  "options": [],
  "answer": "正确",
  "answer_raw": "正确",
  "explanation": "$\\mathbb{R}^3$ 是有限维赋范空间，所有有限维赋范空间在标准距离下都是完备的，因此是完备距离空间。",
  "note": null,
  "explanation_model": "mimo-v2.5-pro",
  "explanation_raw": "{\"explanation\":\"$\\mathbb{R}^3$ 是有限维赋范空间，所有有限维赋范空间在标准距离下都是完备的，因此是完备距离空间。\"}"
}